[
    {
       "name":"Josh",
       "age":32,
       "title":"Software Engineer",
       "join_date":"2018-03-23",
       "active":true
    },
    {
        "name":"Lili",
        "age":24,
        "title":"Frontend Developer",
        "join_date":"2023-01-12",
        "active":true
     },
     {
        "name":"Tom",
        "age":28,
        "title":"Backend Developer",
        "join_date":"2022-11-18",
        "active":false
     },
     {
        "name":"Jack",
        "age":35,
        "title":"Devops Engineer",
        "join_date":"2021-04-07",
        "active":true
     }
 ]